gmaps_route/__init__.py
gmaps_route/nodes/abc_node.py
gmaps_route/nodes/leaf.py
gmaps_route/nodes/node.py
gmaps_route/nodes/root_node.py
gmaps_route/route/destination.py
gmaps_route/route/exceptions.py
gmaps_route/route/leaf_item.py
gmaps_route/route/map.py
gmaps_route/route/node_item.py
gmaps_route/route/route.py
gmaps_route/route/route_point.py
gmaps_route/route/subdestination.py
gmaps_route/route/transportation.py
gmaps_route-0.1.1.dist-info/LICENSE
gmaps_route-0.1.1.dist-info/METADATA
gmaps_route-0.1.1.dist-info/WHEEL
gmaps_route-0.1.1.dist-info/RECORD
