Metadata-Version: 2.3
Name: gmaps-route
Version: 0.1.1
Summary: Easily create Google Maps routes using Python
Author: Lukas Voegl
Author-email: lukas@voegl.org
Requires-Python: >=3.9,<4.0
Classifier: Programming Language :: Python :: 3
Classifier: Programming Language :: Python :: 3.9
Classifier: Programming Language :: Python :: 3.10
Classifier: Programming Language :: Python :: 3.11
Classifier: Programming Language :: Python :: 3.12
Classifier: Programming Language :: Python :: 3.13
